sanic_fcm/__init__.py
sanic_fcm/__meta__.py
sanic_fcm/errors.py
sanic_fcm/fcm.py
sanic_fcm-0.0.6.dist-info/LICENSE.txt
sanic_fcm-0.0.6.dist-info/METADATA
sanic_fcm-0.0.6.dist-info/WHEEL
sanic_fcm-0.0.6.dist-info/top_level.txt
sanic_fcm-0.0.6.dist-info/RECORD
