Metadata-Version: 2.1
Name: sanic-fcm
Version: 0.0.6
Summary: Sanic Python client for FCM - Firebase Cloud Messaging (Android & iOS)..
Home-page: https://github.com/asmodius/sanic-fcm
Author: Asmodius
Author-email: asmodius.a@gmail.com
License: MIT License
Keywords: sanic firebase fcm apns ios gcm android push notifications
Platform: all
Classifier: Development Status :: 5 - Production/Stable
Classifier: Intended Audience :: Developers
Classifier: Operating System :: OS Independent
Classifier: License :: OSI Approved :: MIT License
Classifier: Topic :: Software Development :: Libraries :: Python Modules
Classifier: Programming Language :: Python
Classifier: Programming Language :: Python :: 3
Classifier: Programming Language :: Python :: 3.5
Classifier: Programming Language :: Python :: 3.6
Classifier: Programming Language :: Python :: 3.7
Requires-Dist: aiohttp (>=3.4.0)
